osadl_matrix/__init__.py
osadl_matrix/osadl-matrix.csv
osadl_matrix/osadl-matrix.json
osadl_matrix-2024.5.22.10535.dist-info/LICENSE.Unlicensed
osadl_matrix-2024.5.22.10535.dist-info/LICENSE.ccby40
osadl_matrix-2024.5.22.10535.dist-info/METADATA
osadl_matrix-2024.5.22.10535.dist-info/WHEEL
osadl_matrix-2024.5.22.10535.dist-info/top_level.txt
osadl_matrix-2024.5.22.10535.dist-info/RECORD
