Metadata-Version: 2.1
Name: osadl-matrix
Version: 2024.5.22.10535
Summary: OSADL license compatibility matrix
Author: Konrad Weihmann
Author-email: kweihmann@outlook.com
Classifier: Development Status :: 4 - Beta
Classifier: Intended Audience :: Legal Industry
Classifier: License :: OSI Approved :: The Unlicense (Unlicense)
Classifier: Natural Language :: English
Classifier: Operating System :: OS Independent
Classifier: Programming Language :: Python :: 3 :: Only
Classifier: Programming Language :: Python :: 3
Classifier: Topic :: Database
License-File: LICENSE.ccby40
License-File: LICENSE.Unlicensed
Provides-Extra: dev
Requires-Dist: deepdiff ==7.0.1 ; extra == 'dev'
Requires-Dist: dlint ==0.14.1 ; extra == 'dev'
Requires-Dist: flake8 ==7.0.0 ; extra == 'dev'
Requires-Dist: flake8-2020 ==1.8.1 ; extra == 'dev'
Requires-Dist: flake8-bandit ==4.1.1 ; extra == 'dev'
Requires-Dist: flake8-broken-line ==1.0.0 ; extra == 'dev'
Requires-Dist: flake8-bugbear ==24.4.26 ; extra == 'dev'
Requires-Dist: flake8-builtins ==2.5.0 ; extra == 'dev'
Requires-Dist: flake8-coding ==1.3.2 ; extra == 'dev'
Requires-Dist: flake8-commas ==4.0.0 ; extra == 'dev'
Requires-Dist: flake8-comprehensions ==3.14.0 ; extra == 'dev'
Requires-Dist: flake8-debugger ==4.1.2 ; extra == 'dev'
Requires-Dist: flake8-docstrings ==1.7.0 ; extra == 'dev'
Requires-Dist: flake8-eradicate ==1.5.0 ; extra == 'dev'
Requires-Dist: flake8-executable ==2.1.3 ; extra == 'dev'
Requires-Dist: flake8-fixme ==1.1.1 ; extra == 'dev'
Requires-Dist: flake8-functions ==0.0.8 ; extra == 'dev'
Requires-Dist: flake8-isort ==6.1.1 ; extra == 'dev'
Requires-Dist: flake8-logging-format ==0.9.0 ; extra == 'dev'
Requires-Dist: flake8-mutable ==1.2.0 ; extra == 'dev'
Requires-Dist: flake8-pep3101 ==2.1.0 ; extra == 'dev'
Requires-Dist: flake8-print ==5.0.0 ; extra == 'dev'
Requires-Dist: flake8-quotes ==3.4.0 ; extra == 'dev'
Requires-Dist: flake8-requirements ==2.2.0 ; extra == 'dev'
Requires-Dist: flake8-string-format ==0.3.0 ; extra == 'dev'
Requires-Dist: flake8-variables-names ==0.0.6 ; extra == 'dev'
Requires-Dist: pytest ==8.2.1 ; extra == 'dev'
Requires-Dist: pytest-cov ==5.0.0 ; extra == 'dev'
Requires-Dist: pytest-forked ==1.6.0 ; extra == 'dev'
Requires-Dist: pytest-icdiff ==0.9 ; extra == 'dev'
Requires-Dist: pytest-random-order ==1.1.1 ; extra == 'dev'
Requires-Dist: pytest-socket ==0.7.0 ; extra == 'dev'
Requires-Dist: pytest-sugar ==1.0.0 ; extra == 'dev'
Requires-Dist: pytest-tldr ==0.2.5 ; extra == 'dev'
Requires-Dist: requests ==2.32.1 ; extra == 'dev'
Requires-Dist: twine ==5.1.0 ; extra == 'dev'
Requires-Dist: urllib3 ==2.2.1 ; extra == 'dev'
